<?xml version="1.0" encoding="UTF-8"?>
<beans xmlns="http://www.springframework.org/schema/beans"
	xmlns:xsi="http://www.w3.org/2001/XMLSchema-instance" xmlns:p="http://www.springframework.org/schema/p"
	xmlns:aop="http://www.springframework.org/schema/aop" xmlns:tx="http://www.springframework.org/schema/tx"
	xsi:schemaLocation="http://www.springframework.org/schema/beans 
	                    http://www.springframework.org/schema/beans/spring-beans-2.5.xsd
                        http://www.springframework.org/schema/aop 
                        http://www.springframework.org/schema/aop/spring-aop-2.5.xsd
                        http://www.springframework.org/schema/tx 
                        http://www.springframework.org/schema/tx/spring-tx-2.5.xsd">

	<bean id="dataSource" class="com.mchange.v2.c3p0.ComboPooledDataSource"
		destroy-method="close">
		<property name="identityToken" value="communication-oracle" />
		<property name="driverClass" value="${jdbc.driverClassName}" />
		<property name="jdbcUrl" value="${jdbc.url}" />
		<property name="maxPoolSize" value="${jdbc.maxPoolSize}" />
		<property name="testConnectionOnCheckin" value="${jdbc.testConnectionOnCheckin}" />
		<property name="idleConnectionTestPeriod" value="${jdbc.idleConnectionTestPeriod}" />
		<property name="numHelperThreads" value="${jdbc.numHelperThreads}" />
		<property name="preferredTestQuery" value="${jdbc.preferredTestQuery}" />
		<property name="user" value="${jdbc.username}" />
		<property name="password" value="${jdbc.password}" />
	</bean>


	<bean id="sessionFactory"
		class="org.springframework.orm.hibernate4.LocalSessionFactoryBean">
		<property name="dataSource">
			<ref bean="dataSource" />
		</property>

		<property name="annotatedClasses">
			<list>
				<value>com.eharmony.services.configservice.model.ConfigurationDo
				</value>
			</list>
		</property>

		<property name="hibernateProperties">
			<map>
				<entry key="hibernate.dialect" value="org.hibernate.dialect.Oracle9Dialect" />
				<entry key="hibernate.cache.use_query_cache" value="false" />
				<entry key="hibernate.cache.use_second_level_cache" value="false" />
				<entry key="hibernate.show_sql" value="true" />
				<entry key="hibernate.generate_statistics" value="false" />
			</map>
		</property>
	</bean>

	<tx:annotation-driven />
	<bean id="transactionManager"
		class="org.springframework.orm.hibernate4.HibernateTransactionManager">
		<property name="sessionFactory" ref="sessionFactory" />
	</bean>

</beans>
